{
    "OBJ": "32784",
    "VER": "1.00",
    "CAP": "1",
    "NAME": "CO2-S SCD30 Sensor",
    "SNS": [{
            "NAME": "CO2",
            "MFI": "Sensirion",
            "PART": "SCD30",
            "REGSIZE": "1",
            "ADDRESS": "",
            "BOMID": "1234",
            "CLS": "772",
            "VSPEC": "1234",
            "SAID": "0",
            "UNIT": "ppm",
            "FORMAT": "integer",
            "REPORTRATE": "1000",
            "TYPE": "INPUT",
            "ACCURACY": "2",
            "MIN":"400",
            "MAX":"8000"
        },
        {
            "NAME": "Temperature",
            "MFI": "Sensirion",
            "PART": "SCD30",
            "REGSIZE": "1",
            "ADDRESS": "",
            "BOMID": "1234",
            "CLS": "256",
            "VSPEC": "1234",
            "SAID": "1",
            "UNIT": "C",
            "FORMAT": "float",
            "REPORTRATE": "1000",
            "TYPE": "INPUT",
            "MIN":"-25",
            "MAX":"150"
        },
        {
            "NAME": "Humidity",
            "MFI": "Sensirion",
            "PART": "SCD30",
            "REGSIZE": "1",
            "ADDRESS": "64",
            "BOMID": "1234",
            "CLS": "512",
            "VSPEC": "1234",
            "SAID": "2",
            "UNIT": "%",
            "FORMAT": "float",
            "REPORTRATE": "1000",
            "TYPE": "INPUT",
            "MIN":"0",
            "MAX":"100"
        },
        {
            "NAME": "Ambient Light",
            "MFI": "Rohm Semiconductor",
            "PART": "BH1730",
            "REGSIZE": "1",
            "ADDRESS": "",
            "BOMID": "1234",
            "CLS": "1024",
            "VSPEC": "1234",
            "SAID": "3",
            "FORMAT": "integer",
            "REPORTRATE": "1000",
            "TYPE": "INPUT",
            "UNIT": "LUX",
            "ACCURACY": "0",
            "MIN": "0",
            "MAX": "100000"
        }
    ]
}
